timyton/__init__.py
timyton/__main__.py
timyton/app.py
timyton/data.py
timyton/utils.py
timyton-0.1.0.dist-info/entry_points.txt
timyton-0.1.0.dist-info/LICENSE
timyton-0.1.0.dist-info/WHEEL
timyton-0.1.0.dist-info/METADATA
timyton-0.1.0.dist-info/RECORD
