Metadata-Version: 2.3
Name: timyton
Version: 0.1.0
Summary: A TUI to manage timesheet in Tryton
Author: B2CK
Author-email: Nicolas Évrard <nicolas.evrard@b2ck.com>
Requires-Python: >=3.11
Classifier: Development Status :: 4 - Beta
Classifier: Environment :: Console
Classifier: Framework :: Tryton
Classifier: License :: OSI Approved :: European Union Public Licence 1.2 (EUPL 1.2)
Requires-Dist: textual
Requires-Dist: httpx
Requires-Dist: xdg-base-dirs
